.gitignore
CHANGES.txt
MANIFEST.in
README.rst
bootstrap.py
buildout.cfg
setup.py
isotoma/__init__.py
isotoma.recipe.ploneprefetch.egg-info/PKG-INFO
isotoma.recipe.ploneprefetch.egg-info/SOURCES.txt
isotoma.recipe.ploneprefetch.egg-info/dependency_links.txt
isotoma.recipe.ploneprefetch.egg-info/entry_points.txt
isotoma.recipe.ploneprefetch.egg-info/namespace_packages.txt
isotoma.recipe.ploneprefetch.egg-info/not-zip-safe
isotoma.recipe.ploneprefetch.egg-info/requires.txt
isotoma.recipe.ploneprefetch.egg-info/top_level.txt
isotoma/recipe/__init__.py
isotoma/recipe/ploneprefetch/__init__.py