Metadata-Version: 1.0
Name: isotoma.recipe.ploneprefetch
Version: 0.0.3
Summary: ZC Buildout recipe for installing Plone quickly
Home-page: http://github.com/isotoma/isotoma.recipe.ploneprefetch
Author: John Carr
Author-email: john.carr@isotoma.com
License: ZPL 2.1
Keywords: zope2 buildout
Platform: UNKNOWN
Classifier: Framework :: Buildout
Classifier: Framework :: Buildout :: Recipe
Classifier: Framework :: Plone
Classifier: Framework :: Zope2
Classifier: Programming Language :: Python
